kitchen/__init__.py
kitchen/config/__init__.py
kitchen/config/manager.py
kitchen/config/models.py
kitchen/k8s/__init__.py
kitchen/k8s/base_node.py
kitchen/k8s/handlers/__init__.py
kitchen/k8s/handlers/base.py
kitchen/k8s/handlers/crio.py
kitchen/k8s/handlers/kube_apiserver_cert.py
kitchen/k8s/handlers/kubernetes_components.py
kitchen/k8s/handlers/tailscale.py
kitchen/k8s/main.py
kitchen/k8s/master.py
kitchen/k8s/nodes/__init__.py
kitchen/k8s/nodes/pre_check.py
kitchen/k8s/nodes/worker_pre_check.py
kitchen/k8s/worker.py
kitchen/main.py
kitchen/node_manager/__init__.py
kitchen/node_manager/alembic.ini
kitchen/node_manager/api.py
kitchen/node_manager/cli.py
kitchen/node_manager/connectivity.py
kitchen/node_manager/database.py
kitchen/node_manager/k8s_client.py
kitchen/node_manager/main.py
kitchen/node_manager/manifests/__init__.py
kitchen/node_manager/manifests/k8s-manifests.yaml
kitchen/node_manager/migrations/env.py
kitchen/node_manager/migrations/script.py.mako
kitchen/node_manager/migrations/versions/001_initial_schema.py
kitchen/node_manager/models.py
kitchen/node_manager/worker.py
kitchen/ssh.py
k8s_kitchen-0.2.0.dist-info/METADATA
k8s_kitchen-0.2.0.dist-info/WHEEL
k8s_kitchen-0.2.0.dist-info/entry_points.txt
k8s_kitchen-0.2.0.dist-info/RECORD
