Metadata-Version: 2.3
Name: k8s-kitchen
Version: 0.2.0
Summary: Your Kubernetes cookbook for cluster management
Author: User
Author-email: user@example.com
Requires-Python: >=3.9
Classifier: Programming Language :: Python :: 3
Classifier: Programming Language :: Python :: 3.9
Classifier: Programming Language :: Python :: 3.10
Classifier: Programming Language :: Python :: 3.11
Classifier: Programming Language :: Python :: 3.12
Classifier: Programming Language :: Python :: 3.13
Requires-Dist: paramiko (>=3.5.1,<4.0.0)
Requires-Dist: pyyaml (>=6.0.2,<7.0.0)
Requires-Dist: typer (>=0.16.0)
